airo_ipc/__init__.py
airo_ipc/py.typed
airo_ipc/cyclone_shm/__init__.py
airo_ipc/cyclone_shm/defaults.py
airo_ipc/cyclone_shm/idl/__init__.py
airo_ipc/cyclone_shm/idl/defaults/__init__.py
airo_ipc/cyclone_shm/idl/defaults/buffer_nr.py
airo_ipc/cyclone_shm/idl_shared_memory/__init__.py
airo_ipc/cyclone_shm/idl_shared_memory/base_idl.py
airo_ipc/cyclone_shm/patterns/__init__.py
airo_ipc/cyclone_shm/patterns/ddsreader.py
airo_ipc/cyclone_shm/patterns/ddswriter.py
airo_ipc/cyclone_shm/patterns/sm_reader.py
airo_ipc/cyclone_shm/patterns/sm_writer.py
airo_ipc/framework/__init__.py
airo_ipc/framework/framework.py
airo_ipc/framework/node.py
airo_ipc-0.2.0.dist-info/licenses/LICENSE
examples/framework/airo_mono.py
examples/framework/webcam.py
airo_ipc-0.2.0.dist-info/METADATA
airo_ipc-0.2.0.dist-info/WHEEL
airo_ipc-0.2.0.dist-info/top_level.txt
airo_ipc-0.2.0.dist-info/RECORD
