Metadata-Version: 2.4
Name: airo-ipc
Version: 0.2.0
Summary: IPC framework for AIRO.
Author-email: Matthijs Biondina <matthijs.biondina@ugent.be>, Mathieu De Coster <mathieu.decoster@ugent.be>
Project-URL: Homepage, https://github.com/airo-ugent/airo-ipc
Project-URL: Issues, https://github.com/airo-ugent/airo-ipc/issues
Classifier: Programming Language :: Python :: 3
Classifier: License :: OSI Approved :: MIT License
Classifier: Operating System :: OS Independent
Requires-Python: >=3.9
License-File: LICENSE
Requires-Dist: cyclonedds-nightly==2025.6.6
Requires-Dist: loguru>=0.7.2
Requires-Dist: numpy
Dynamic: license-file
